vexipy/__init__.py
vexipy/_iri.py
vexipy/_util.py
vexipy/component.py
vexipy/document.py
vexipy/py.typed
vexipy/statement.py
vexipy/status.py
vexipy/vulnerability.py
vexipy-0.2.0.dist-info/METADATA
vexipy-0.2.0.dist-info/WHEEL
vexipy-0.2.0.dist-info/licenses/LICENSE
vexipy-0.2.0.dist-info/RECORD
