Metadata-Version: 2.4
Name: vexipy
Version: 0.2.0
Summary: Python OpenVEX Library
Author-email: Colin Pinnell McAllister <colinmca242@gmail.com>
License-File: LICENSE
Keywords: openvex,security,vex,vulnerability
Classifier: Development Status :: 3 - Alpha
Classifier: Intended Audience :: Developers
Classifier: License :: OSI Approved :: MIT License
Classifier: Programming Language :: Python :: 3
Classifier: Programming Language :: Python :: 3.9
Classifier: Programming Language :: Python :: 3.10
Classifier: Programming Language :: Python :: 3.11
Classifier: Programming Language :: Python :: 3.12
Classifier: Programming Language :: Python :: 3.13
Requires-Python: >=3.9
Requires-Dist: pydantic>=2.11.1
Requires-Dist: rfc3987>=1.3.8
